asycont600-0.8.1.dist-info/METADATA
asycont600-0.8.1.dist-info/WHEEL
asycont600-0.8.1.dist-info/entry_points.txt
asycont600-0.8.1.dist-info/licenses/LICENSE
asycont600/__init__.py
asycont600/__main__.py
asycont600-0.8.1.dist-info/RECORD
