Metadata-Version: 2.1
Name: ASYCONT600
Version: 0.8.1
Summary: ASYCONT600 Axis Control Unit Instrument Interface
Author-Email: =?utf-8?b?SMO8c2V5aW4gWcSwxJ7EsFQ=?= <yigit.hsyn@gmail.com>
License: MIT
Classifier: Development Status :: 1 - Planning
Classifier: Programming Language :: Python :: 3.12
Classifier: Programming Language :: Python :: Implementation :: CPython
Classifier: License :: OSI Approved :: MIT License
Classifier: Topic :: System :: Hardware
Classifier: Environment :: Console
Requires-Python: >=3.12
